nonebot_plugin_helldivers/__init__.py
nonebot_plugin_helldivers/api.py
nonebot_plugin_helldivers/config.py
nonebot_plugin_helldivers/info.py
nonebot_plugin_helldivers/utils.py
nonebot_plugin_helldivers-1.2.0.dist-info/LICENSE
nonebot_plugin_helldivers-1.2.0.dist-info/METADATA
nonebot_plugin_helldivers-1.2.0.dist-info/WHEEL
nonebot_plugin_helldivers-1.2.0.dist-info/RECORD
