Metadata-Version: 2.1
Name: nonebot-plugin-helldivers
Version: 1.2.0
Summary: 为了超级地球！
License: MIT
Author: SherkeyXD
Author-email: 253294679@qq.com
Requires-Python: >=3.9,<4.0
Classifier: License :: OSI Approved :: MIT License
Classifier: Programming Language :: Python :: 3
Classifier: Programming Language :: Python :: 3.9
Classifier: Programming Language :: Python :: 3.10
Classifier: Programming Language :: Python :: 3.11
Classifier: Programming Language :: Python :: 3.12
Requires-Dist: aiohttp (>=3.7.4,<4.0.0)
Requires-Dist: nonebot-plugin-send-anything-anywhere (>=0.6.0,<0.7.0)
Requires-Dist: nonebot2 (>=2.1.0,<3.0.0)
Requires-Dist: nonebot_plugin_htmlrender (>=0.3.0,<0.4.0)
